ibm2ieee-1.3.3.dist-info/RECORD
ibm2ieee-1.3.3.dist-info/WHEEL
ibm2ieee-1.3.3.dist-info/top_level.txt
ibm2ieee-1.3.3.dist-info/LICENSE.txt
ibm2ieee-1.3.3.dist-info/METADATA
ibm2ieee/__init__.py
ibm2ieee/_ibm2ieee.c
ibm2ieee/_ibm2ieee.cpython-311-darwin.so
ibm2ieee/test/__init__.py
ibm2ieee/test/test_ibm2ieee.py
