Metadata-Version: 2.1
Name: ibm2ieee
Version: 1.3.3
Summary: Convert IBM hexadecimal floating-point to IEEE 754 floating-point
Author-email: Enthought <info@enthought.com>
License: BSD 3-Clause License
Project-URL: readme, https://github.com/enthought/ibm2ieee/blob/main/README.rst
Project-URL: repository, https://github.com/enthought/ibm2ieee
Project-URL: issues, https://github.com/enthought/ibm2ieee/issues
Keywords: ibm,hfp,ieee754,hexadecimal,floating-point,ufunc
Classifier: Development Status :: 5 - Production/Stable
Classifier: Intended Audience :: Developers
Classifier: License :: OSI Approved :: BSD License
Classifier: Operating System :: OS Independent
Classifier: Programming Language :: Python :: 3
Requires-Python: >=3.7
License-File: LICENSE.txt
Requires-Dist: numpy
